makepics.py
cubeinspect-0.1.3.dist-info/LICENSE
cubeinspect-0.1.3.dist-info/METADATA
cubeinspect-0.1.3.dist-info/WHEEL
cubeinspect-0.1.3.dist-info/entry_points.txt
cubeinspect-0.1.3.dist-info/top_level.txt
cubeinspect-0.1.3.dist-info/RECORD
